template_manager/__init__.py
template_manager-1.0.1.dist-info/LICENSE
template_manager-1.0.1.dist-info/METADATA
template_manager-1.0.1.dist-info/WHEEL
template_manager-1.0.1.dist-info/top_level.txt
template_manager-1.0.1.dist-info/RECORD
